mkdocs_minify_plugin/__init__.py
mkdocs_minify_plugin/plugin.py
mkdocs_minify_plugin-0.7.2.dist-info/LICENSE
mkdocs_minify_plugin-0.7.2.dist-info/METADATA
mkdocs_minify_plugin-0.7.2.dist-info/WHEEL
mkdocs_minify_plugin-0.7.2.dist-info/entry_points.txt
mkdocs_minify_plugin-0.7.2.dist-info/top_level.txt
mkdocs_minify_plugin-0.7.2.dist-info/RECORD
