Metadata-Version: 2.1
Name: mkdocs-minify-plugin
Version: 0.7.2
Summary: An MkDocs plugin to minify HTML, JS or CSS files prior to being written to disk
Home-page: https://github.com/byrnereese/mkdocs-minify-plugin
Author: Byrne Reese, Lars Wilhelmer
Author-email: byrne@majordojo.com
License: MIT
Keywords: mkdocs minify publishing documentation html css
Classifier: Development Status :: 4 - Beta
Classifier: Intended Audience :: Developers
Classifier: Intended Audience :: Information Technology
Classifier: License :: OSI Approved :: MIT License
Classifier: Programming Language :: Python
Classifier: Programming Language :: Python :: 3 :: Only
Classifier: Programming Language :: Python :: 3.8
Classifier: Programming Language :: Python :: 3.9
Classifier: Programming Language :: Python :: 3.10
Classifier: Programming Language :: Python :: 3.11
Requires-Python: >=3.8
License-File: LICENSE
